{
  "repo": "google",
  "feeds": [
    {
      "source": "https://developers.googleblog.com/en/",
      "feed_url": "https://developers.googleblog.com/feed/",
      "saved": 10,
      "title": "Google Developers Blog"
    },
    {
      "source": "https://blog.google/innovation-and-ai/technology/developers-tools/",
      "feed_url": "https://blog.google/innovation-and-ai/technology/developers-tools/rss/",
      "saved": 10,
      "title": "Google Blog – Developers & Tools"
    }
  ],
  "post_count": 10,
  "fetched": "2026-05-03T23:28:40Z"
}